magicsound.py
magicsound-0.0.5.dist-info/LICENSE
magicsound-0.0.5.dist-info/METADATA
magicsound-0.0.5.dist-info/WHEEL
magicsound-0.0.5.dist-info/top_level.txt
magicsound-0.0.5.dist-info/RECORD
