Metadata-Version: 2.1
Name: magicsound
Version: 0.0.5
Summary: Super simple sound player
Home-page: https://github.com/jhanish/magicsound
Author: Joe Hanish
Author-email: joe.hanish@gmail.com
License: UNKNOWN
Keywords: sound magicsound playsound music wave wav mp3 media song play audio
Platform: UNKNOWN
Classifier: Programming Language :: Python :: 3
Classifier: License :: OSI Approved :: MIT License
Classifier: Operating System :: OS Independent
Requires-Python: >=3.6
